README.rst
setup.py
gusregon/__init__.py
gusregon/gus.py
gusregon/version.py
gusregon.egg-info/PKG-INFO
gusregon.egg-info/SOURCES.txt
gusregon.egg-info/dependency_links.txt
gusregon.egg-info/not-zip-safe
gusregon.egg-info/requires.txt
gusregon.egg-info/top_level.txt
tests/__init__.py
tests/test_api.py