Metadata-Version: 1.1
Name: gusregon
Version: 1.1.3
Summary: GUS REGON Internet Database Client
Home-page: https://github.com/bogdal/gusregon
Author: Adam Bogdał
Author-email: adam@bogdal.pl
License: UNKNOWN
Platform: UNKNOWN
Classifier: Environment :: Web Environment
Classifier: Intended Audience :: Developers
Classifier: License :: OSI Approved :: BSD License
Classifier: Operating System :: OS Independent
Classifier: Programming Language :: Python
Classifier: Programming Language :: Python :: 2
Classifier: Programming Language :: Python :: 3
Classifier: Topic :: Software Development :: Libraries :: Python Modules
Classifier: Topic :: Utilities
